odoo10_addon_product_multi_image-10.0.1.0.0.99.dev5-py2.7-nspkg.pth
odoo/addons/product_multi_image/README.rst
odoo/addons/product_multi_image/__init__.py
odoo/addons/product_multi_image/__manifest__.py
odoo/addons/product_multi_image/hooks.py
odoo/addons/product_multi_image/i18n/es.po
odoo/addons/product_multi_image/i18n/product_multi_image.pot
odoo/addons/product_multi_image/i18n/sv.po
odoo/addons/product_multi_image/images/db.png
odoo/addons/product_multi_image/images/file.png
odoo/addons/product_multi_image/images/product.png
odoo/addons/product_multi_image/images/url.png
odoo/addons/product_multi_image/models/__init__.py
odoo/addons/product_multi_image/models/image.py
odoo/addons/product_multi_image/models/product_product.py
odoo/addons/product_multi_image/models/product_template.py
odoo/addons/product_multi_image/static/description/icon.png
odoo/addons/product_multi_image/static/description/icon.svg
odoo/addons/product_multi_image/tests/__init__.py
odoo/addons/product_multi_image/tests/test_product_multi_image.py
odoo/addons/product_multi_image/views/image_view.xml
odoo/addons/product_multi_image/views/product_template_view.xml
odoo10_addon_product_multi_image-10.0.1.0.0.99.dev5.dist-info/METADATA
odoo10_addon_product_multi_image-10.0.1.0.0.99.dev5.dist-info/RECORD
odoo10_addon_product_multi_image-10.0.1.0.0.99.dev5.dist-info/WHEEL
odoo10_addon_product_multi_image-10.0.1.0.0.99.dev5.dist-info/namespace_packages.txt
odoo10_addon_product_multi_image-10.0.1.0.0.99.dev5.dist-info/top_level.txt
